nagini_contracts/__init__.py
nagini_contracts/adt.py
nagini_contracts/contracts.py
nagini_contracts/importer.py
nagini_contracts/io_builtins.py
nagini_contracts/io_contracts.py
nagini_contracts/lock.py
nagini_contracts/obligations.py
nagini_contracts/py.typed
nagini_contracts/thread.py
nagini_contracts/transformer.py
nagini_translation/__init__.py
nagini_translation/analyzer.py
nagini_translation/analyzer_io.py
nagini_translation/client.py
nagini_translation/conftest.py
nagini_translation/main.py
nagini_translation/sif_translator.py
nagini_translation/tests.py
nagini_translation/translator.py
nagini_translation/verifier.py
nagini_translation/external/__init__.py
nagini_translation/external/ast_util.py
nagini_translation/lib/__init__.py
nagini_translation/lib/config.py
nagini_translation/lib/constants.py
nagini_translation/lib/context.py
nagini_translation/lib/guard_collectors.py
nagini_translation/lib/io_checkers.py
nagini_translation/lib/io_context.py
nagini_translation/lib/jvmaccess.py
nagini_translation/lib/obligation_context.py
nagini_translation/lib/program_nodes.py
nagini_translation/lib/resolver.py
nagini_translation/lib/typedefs.py
nagini_translation/lib/typeinfo.py
nagini_translation/lib/util.py
nagini_translation/lib/views.py
nagini_translation/lib/viper_ast.py
nagini_translation/lib/errors/__init__.py
nagini_translation/lib/errors/manager.py
nagini_translation/lib/errors/messages.py
nagini_translation/lib/errors/rules.py
nagini_translation/lib/errors/wrappers.py
nagini_translation/lib/silver_nodes/__init__.py
nagini_translation/lib/silver_nodes/base.py
nagini_translation/lib/silver_nodes/bool_expr.py
nagini_translation/lib/silver_nodes/call.py
nagini_translation/lib/silver_nodes/expression.py
nagini_translation/lib/silver_nodes/int_cmp_expr.py
nagini_translation/lib/silver_nodes/int_expr.py
nagini_translation/lib/silver_nodes/location_expr.py
nagini_translation/lib/silver_nodes/perm_cmp_expr.py
nagini_translation/lib/silver_nodes/perm_expr.py
nagini-1.1.1.dist-info/LICENSE.txt
nagini-1.1.1.dist-info/METADATA
nagini-1.1.1.dist-info/WHEEL
nagini-1.1.1.dist-info/entry_points.txt
nagini-1.1.1.dist-info/top_level.txt
nagini-1.1.1.dist-info/RECORD
