Metadata-Version: 2.1
Name: nagini
Version: 1.1.1
Summary: Static verifier for Python 3, based on Viper.
Home-page: http://www.pm.inf.ethz.ch/research/nagini.html
Author: Viper Team
Author-email: viper@inf.ethz.ch
License: MPL-2.0
Classifier: Development Status :: 4 - Beta
Classifier: Environment :: Console
Classifier: Intended Audience :: Developers
Classifier: License :: OSI Approved :: Mozilla Public License 2.0 (MPL 2.0)
Classifier: Operating System :: OS Independent
Classifier: Programming Language :: Python :: 3.9
Classifier: Topic :: Software Development
Requires: distribute
License-File: LICENSE.txt
Requires-Dist: mypy ==0.782
Requires-Dist: toposort ==1.5
Requires-Dist: jpype1 ==1.2.1
Requires-Dist: astunparse ==1.6.2
Requires-Dist: pytest ==4.3.0
Requires-Dist: pytest-xdist ==1.27.0
Requires-Dist: z3-solver ==4.8.7.0
